proxy/__init__.py
proxy/__main__.py
proxy/proxy.py
proxy/py.typed
proxy/common/.gitignore
proxy/common/__init__.py
proxy/common/_scm_version.py
proxy/common/_scm_version.pyi
proxy/common/_version.py
proxy/common/backports.py
proxy/common/constants.py
proxy/common/flag.py
proxy/common/logger.py
proxy/common/pki.py
proxy/common/plugins.py
proxy/common/types.py
proxy/common/utils.py
proxy/common/version.py
proxy/core/__init__.py
proxy/core/acceptor/__init__.py
proxy/core/acceptor/acceptor.py
proxy/core/acceptor/pool.py
proxy/core/base/__init__.py
proxy/core/base/tcp_server.py
proxy/core/base/tcp_tunnel.py
proxy/core/base/tcp_upstream.py
proxy/core/connection/__init__.py
proxy/core/connection/client.py
proxy/core/connection/connection.py
proxy/core/connection/pool.py
proxy/core/connection/server.py
proxy/core/connection/types.py
proxy/core/event/__init__.py
proxy/core/event/dispatcher.py
proxy/core/event/manager.py
proxy/core/event/metrics.py
proxy/core/event/names.py
proxy/core/event/queue.py
proxy/core/event/subscriber.py
proxy/core/listener/__init__.py
proxy/core/listener/base.py
proxy/core/listener/pool.py
proxy/core/listener/tcp.py
proxy/core/listener/unix.py
proxy/core/ssh/__init__.py
proxy/core/ssh/base.py
proxy/core/ssh/handler.py
proxy/core/ssh/listener.py
proxy/core/tls/__init__.py
proxy/core/tls/certificate.py
proxy/core/tls/finished.py
proxy/core/tls/handshake.py
proxy/core/tls/hello.py
proxy/core/tls/key_exchange.py
proxy/core/tls/pretty.py
proxy/core/tls/tls.py
proxy/core/tls/types.py
proxy/core/work/__init__.py
proxy/core/work/delegate.py
proxy/core/work/local.py
proxy/core/work/pool.py
proxy/core/work/remote.py
proxy/core/work/threaded.py
proxy/core/work/threadless.py
proxy/core/work/work.py
proxy/core/work/fd/__init__.py
proxy/core/work/fd/fd.py
proxy/core/work/fd/local.py
proxy/core/work/fd/remote.py
proxy/core/work/task/__init__.py
proxy/core/work/task/handler.py
proxy/core/work/task/local.py
proxy/core/work/task/remote.py
proxy.py-2.4.9.dist-info/METADATA
proxy.py-2.4.9.dist-info/WHEEL
proxy.py-2.4.9.dist-info/entry_points.txt
proxy.py-2.4.9.dist-info/top_level.txt
proxy.py-2.4.9.dist-info/RECORD
