Metadata-Version: 2.1
Name: proxy.py
Version: 2.4.9
Summary: \u26a1 Fast \u2022 \U0001fab6 Lightweight \u2022 \U0001f51f Dependency \u2022 \U0001f50c Pluggable \u2022 \U0001f608 TLS interception \u2022 \U0001f512 DNS-over-HTTPS \u2022 \U0001f525 Poor Mans VPN \u2022 \u23ea Reverse & \u23e9 Forward \u2022 \U0001f46e\U0001f3ff Proxy Server framework \u2022 \U0001f310 Web Server framework \u2022 \u27b5 \u27b6 \u27b7 \u27a0 PubSub framework \u2022 \U0001f477 Work acceptor & executor framework.
Home-page: https://github.com/abhinavsingh/proxy.py
Download-URL: https://github.com/abhinavsingh/proxy.py/archive/master.zip
Author: Abhinav Singh
Author-email: mailsforabhinav+proxy@gmail.com
License: 'BSD'
Project-URL: Container Image: DockerHub, https://hub.docker.com/r/abhinavsingh/proxy.py
Project-URL: Chat: Gitter, https://gitter.im/proxy.py/community
Project-URL: Coverage: Codecov, https://codecov.io/github/abhinavsingh/proxy.py
Project-URL: CI: GitHub, https://github.com/abhinavsingh/proxy.py/actions
Project-URL: Docs: Changelog, https://proxypy.rtfd.io/en/latest/#changelog
Project-URL: Docs: RTD, https://proxypy.rtfd.io/en/latest/
Project-URL: Docs: Intro, https://abhinavsingh.com/proxy-py-a-lightweight-single-file-http-proxy-server-in-python/
Project-URL: GitHub: discussions, https://github.com/abhinavsingh/proxy.py/discussions
Project-URL: GitHub: issues, https://github.com/abhinavsingh/proxy.py/issues
Project-URL: GitHub: repo, https://github.com/abhinavsingh/proxy.py
Keywords: http,proxy,http proxy server,proxy server,http server,http web server,proxy framework,web framework,Python3
Classifier: Development Status :: 5 - Production/Stable
Classifier: Environment :: Console
Classifier: Environment :: No Input/Output (Daemon)
Classifier: Environment :: Web Environment
Classifier: Environment :: MacOS X
Classifier: Environment :: Plugins
Classifier: Environment :: Win32 (MS Windows)
Classifier: Framework :: Robot Framework
Classifier: Framework :: Robot Framework :: Library
Classifier: Intended Audience :: Developers
Classifier: Intended Audience :: Education
Classifier: Intended Audience :: End Users/Desktop
Classifier: Intended Audience :: System Administrators
Classifier: Intended Audience :: Science/Research
Classifier: License :: OSI Approved :: BSD License
Classifier: Natural Language :: English
Classifier: Operating System :: MacOS
Classifier: Operating System :: MacOS :: MacOS 9
Classifier: Operating System :: MacOS :: MacOS X
Classifier: Operating System :: POSIX
Classifier: Operating System :: POSIX :: Linux
Classifier: Operating System :: Unix
Classifier: Operating System :: Microsoft
Classifier: Operating System :: Microsoft :: Windows
Classifier: Operating System :: Microsoft :: Windows :: Windows 10
Classifier: Operating System :: Android
Classifier: Operating System :: OS Independent
Classifier: Programming Language :: Python :: Implementation
Classifier: Programming Language :: Python :: 3 :: Only
Classifier: Programming Language :: Python :: 3
Classifier: Programming Language :: Python :: 3.6
Classifier: Programming Language :: Python :: 3.7
Classifier: Programming Language :: Python :: 3.8
Classifier: Programming Language :: Python :: 3.9
Classifier: Programming Language :: Python :: 3.10
Classifier: Programming Language :: Python :: 3.11
Classifier: Programming Language :: Python :: 3.12
Classifier: Topic :: Internet
Classifier: Topic :: Internet :: Proxy Servers
Classifier: Topic :: Internet :: WWW/HTTP
Classifier: Topic :: Internet :: WWW/HTTP :: Browsers
Classifier: Topic :: Internet :: WWW/HTTP :: Dynamic Content
Classifier: Topic :: Internet :: WWW/HTTP :: Dynamic Content :: CGI Tools/Libraries
Classifier: Topic :: Internet :: WWW/HTTP :: HTTP Servers
Classifier: Topic :: Scientific/Engineering :: Information Analysis
Classifier: Topic :: Software Development :: Debuggers
Classifier: Topic :: Software Development :: Libraries :: Python Modules
Classifier: Topic :: System :: Monitoring
Classifier: Topic :: System :: Networking
Classifier: Topic :: System :: Networking :: Firewalls
Classifier: Topic :: System :: Networking :: Monitoring
Classifier: Topic :: Utilities
Classifier: Typing :: Typed
Requires-Python: >=3.6
Provides-Extra: metrics
Requires-Dist: prometheus_client==0.17.1; python_version < "3.8" and extra == "metrics"
Requires-Dist: prometheus_client==0.20.0; python_version >= "3.8" and extra == "metrics"
Provides-Extra: release
Requires-Dist: setuptools-scm==6.3.2; extra == "release"
Requires-Dist: twine==3.8.0; extra == "release"
Provides-Extra: tunnel
Requires-Dist: paramiko==2.11.0; python_version < "3.11" and extra == "tunnel"
Requires-Dist: paramiko==3.4.0; python_version >= "3.11" and extra == "tunnel"
Requires-Dist: types-paramiko==2.11.3; python_version < "3.11" and extra == "tunnel"
Requires-Dist: types-paramiko==3.4.0.20240311; python_version >= "3.11" and extra == "tunnel"
Requires-Dist: cryptography==36.0.2; python_version <= "3.6" and extra == "tunnel"
Requires-Dist: cryptography==39.0.1; python_version > "3.6" and extra == "tunnel"
Provides-Extra: testing
Requires-Dist: wheel==0.37.1; extra == "testing"
Requires-Dist: python-coveralls==2.9.3; extra == "testing"
Requires-Dist: coverage==6.2; python_version < "3.11" and extra == "testing"
Requires-Dist: coverage==7.4.4; python_version >= "3.11" and extra == "testing"
Requires-Dist: flake8==4.0.1; extra == "testing"
Requires-Dist: pytest==7.0.1; python_version < "3.11" and extra == "testing"
Requires-Dist: pytest-cov==3.0.0; python_version < "3.11" and extra == "testing"
Requires-Dist: pytest-xdist==2.5.0; python_version < "3.11" and extra == "testing"
Requires-Dist: pytest-mock==3.6.1; python_version < "3.11" and extra == "testing"
Requires-Dist: pytest-asyncio==0.16.0; python_version < "3.11" and extra == "testing"
Requires-Dist: pytest==8.1.1; python_version >= "3.11" and extra == "testing"
Requires-Dist: pytest-cov==5.0.0; python_version >= "3.11" and extra == "testing"
Requires-Dist: pytest-xdist==3.5.0; python_version >= "3.11" and extra == "testing"
Requires-Dist: pytest-mock==3.14.0; python_version >= "3.11" and extra == "testing"
Requires-Dist: pytest-asyncio==0.21.1; python_version >= "3.11" and extra == "testing"
Requires-Dist: autopep8==1.6.0; extra == "testing"
Requires-Dist: mypy==0.971; extra == "testing"
Requires-Dist: py-spy==0.3.12; extra == "testing"
Requires-Dist: tox==3.28.0; python_version < "3.11" and extra == "testing"
Requires-Dist: tox==4.14.2; python_version >= "3.11" and extra == "testing"
Requires-Dist: mccabe==0.6.1; extra == "testing"
Requires-Dist: pylint==2.13.7; python_version < "3.11" and extra == "testing"
Requires-Dist: pylint==3.1.0; python_version >= "3.11" and extra == "testing"
Requires-Dist: rope==1.1.1; extra == "testing"
Requires-Dist: httpx==0.22.0; python_version < "3.11" and extra == "testing"
Requires-Dist: httpx==0.27.0; python_version >= "3.11" and extra == "testing"
Requires-Dist: h2==4.1.0; extra == "testing"
Requires-Dist: hpack==4.0.0; extra == "testing"
Requires-Dist: hyperframe==6.0.1; extra == "testing"
Requires-Dist: pre-commit==2.16.0; extra == "testing"
Requires-Dist: types-requests==2.28.11.5; extra == "testing"
Requires-Dist: types-setuptools==64.0.1; extra == "testing"
